MANIFEST.in
README.md
setup.cfg
setup.py
xmastree/__init__.py
xmastree/xmastree.py
xmastree.egg-info/PKG-INFO
xmastree.egg-info/SOURCES.txt
xmastree.egg-info/dependency_links.txt
xmastree.egg-info/entry_points.txt
xmastree.egg-info/not-zip-safe
xmastree.egg-info/requires.txt
xmastree.egg-info/top_level.txt